odoo/addons/l10n_it_withholding_tax/README.rst
odoo/addons/l10n_it_withholding_tax/__init__.py
odoo/addons/l10n_it_withholding_tax/__manifest__.py
odoo/addons/l10n_it_withholding_tax/i18n/it.po
odoo/addons/l10n_it_withholding_tax/i18n/l10n_it_withholding_tax.pot
odoo/addons/l10n_it_withholding_tax/models/__init__.py
odoo/addons/l10n_it_withholding_tax/models/account.py
odoo/addons/l10n_it_withholding_tax/models/withholding_tax.py
odoo/addons/l10n_it_withholding_tax/security/ir.model.access.csv
odoo/addons/l10n_it_withholding_tax/security/security.xml
odoo/addons/l10n_it_withholding_tax/static/description/icon.png
odoo/addons/l10n_it_withholding_tax/static/img/fattura-fornitore-768x517.png
odoo/addons/l10n_it_withholding_tax/static/img/foto-3-1-1024x505.png
odoo/addons/l10n_it_withholding_tax/static/img/ritenuta-acconto-odoo-codifica-768x457.png
odoo/addons/l10n_it_withholding_tax/tests/__init__.py
odoo/addons/l10n_it_withholding_tax/tests/test_withholding_tax.py
odoo/addons/l10n_it_withholding_tax/views/account.xml
odoo/addons/l10n_it_withholding_tax/views/withholding_tax.xml
odoo11_addon_l10n_it_withholding_tax-11.0.1.0.2.dist-info/METADATA
odoo11_addon_l10n_it_withholding_tax-11.0.1.0.2.dist-info/RECORD
odoo11_addon_l10n_it_withholding_tax-11.0.1.0.2.dist-info/WHEEL
odoo11_addon_l10n_it_withholding_tax-11.0.1.0.2.dist-info/top_level.txt
